heat_index/__init__.py
heat_index/calculate.py
heat_index/coefficients.py
heat_index-0.0.1.dist-info/LICENSE
heat_index-0.0.1.dist-info/METADATA
heat_index-0.0.1.dist-info/WHEEL
heat_index-0.0.1.dist-info/top_level.txt
heat_index-0.0.1.dist-info/RECORD
