Metadata-Version: 2.1
Name: heat-index
Version: 0.0.1
Summary: A simple tool to calculate heat index in Python
Home-page: https://github.com/myleshk/heat_index_calculator
Author: Myles Fang
Author-email: i@myles.hk
License: MIT
Download-URL: https://pypi.org/project/heat_index_calculator/
Keywords: HeatIndex
Platform: UNKNOWN
